pdf2gpkg
