Metadata-Version: 2.1
Name: pdf2gpkg
Version: 0.1.0
Summary: extract and georeference geometry from pdf
Home-page: https://github.com/wingechr/pdf2gpkg
Author: Christian Winger
Author-email: c@wingechr.de
License: Public Domain
Platform: any
Classifier: Programming Language :: Python :: 3
Classifier: License :: CC0 1.0 Universal (CC0 1.0) Public Domain Dedication
Classifier: Operating System :: OS Independent
Requires-Dist: PyMuPDF
Requires-Dist: geopandas
Requires-Dist: shapely
